{
  "$schema": "https://static.modelcontextprotocol.io/schemas/2025-07-09/server.schema.json",
  "name": "io.usefulapi/ecwid",
  "description": "Read store products, orders, customers, categories and coupons; adjust inventory and update orders.",
  "version": "1.0.0",
  "repository": {
    "url": "https://github.com/m190/usefulapi-mcp",
    "source": "github",
    "subfolder": "servers/ecwid"
  },
  "remotes": [
    {
      "type": "streamable-http",
      "url": "https://ecwid.usefulapi.io/mcp"
    }
  ]
}
